duckdb_appender/__init__.py
duckdb_appender/appender.py
duckdb_appender/errors.py
duckdb_appender-0.3.1.dist-info/LICENSE
duckdb_appender-0.3.1.dist-info/METADATA
duckdb_appender-0.3.1.dist-info/WHEEL
duckdb_appender-0.3.1.dist-info/top_level.txt
duckdb_appender-0.3.1.dist-info/RECORD
