Metadata-Version: 2.1
Name: duckdb-appender
Version: 0.3.1
Summary: A DuckDB appender for Python
Author-email: Toan Phan <toanphan.dev@gmail.com>
Requires-Python: >=3.9
License-File: LICENSE
Requires-Dist: duckdb >=1.0.0
